nicoclient/__init__.py
nicoclient/core/__init__.py
nicoclient/core/lookup.py
nicoclient/core/search.py
nicoclient/html_page/__init__.py
nicoclient/html_page/html_page.py
nicoclient/html_page/playlist.py
nicoclient/model/__init__.py
nicoclient/model/playlist.py
nicoclient/model/uploader.py
nicoclient/model/video.py
nicoclient/utils/__init__.py
nicoclient/utils/time_utils.py
nicoclient-1.1.9.dist-info/METADATA
nicoclient-1.1.9.dist-info/WHEEL
nicoclient-1.1.9.dist-info/top_level.txt
nicoclient-1.1.9.dist-info/RECORD
