Metadata-Version: 2.1
Name: nicoclient
Version: 1.1.9
Summary: A python client to interact with nicovideo.jp
Home-page: https://github.com/jaeseopark/nicoclient
Author: Jaeseo Park
Author-email: jaeseopark@icloud.com
License: UNKNOWN
Platform: UNKNOWN
Classifier: Programming Language :: Python :: 3
Classifier: Natural Language :: English
Requires-Dist: requests
Requires-Dist: beautifulsoup4
Requires-Dist: python-dateutil
Requires-Dist: pydantic
